app/__init__.py
app/__main__.py
app/app.py
app/backtest/__init__.py
app/backtest/backtest.py
app/backtest/broker.py
app/backtest/engine.py
app/backtest/exceptions.py
app/backtest/feed.py
app/data_bundle/__init__.py
app/data_bundle/__main__.py
app/data_bundle/yahoo_demo_bundle.py
zipline_foreverbull-0.0.1.dist-info/LICENSE
zipline_foreverbull-0.0.1.dist-info/METADATA
zipline_foreverbull-0.0.1.dist-info/WHEEL
zipline_foreverbull-0.0.1.dist-info/top_level.txt
zipline_foreverbull-0.0.1.dist-info/RECORD
