Metadata-Version: 2.1
Name: zipline-foreverbull
Version: 0.0.1
Summary: Zipline API to be use for Foreverbull
Home-page: UNKNOWN
Author: Henrik Nilsson
Author-email: henrik@lhjnilsson.com
License: UNKNOWN
Platform: UNKNOWN
Classifier: Programming Language :: Python :: 3.8
Classifier: Programming Language :: Python :: 3.9
Requires-Python: >=3.6
License-File: LICENSE
Requires-Dist: zipline-reloaded (>=2.1.1)
Requires-Dist: foreverbull-core (>=0.0.12)
